pycartnext/__init__.py
pycartnext/cart.py
pycartnext/db.py
pycartnext/json_encoder.py
pycartnext/logger.py
pycartnext/schemas.py
pycartnext-0.1.1.dist-info/LICENSE
pycartnext-0.1.1.dist-info/METADATA
pycartnext-0.1.1.dist-info/WHEEL
pycartnext-0.1.1.dist-info/RECORD
