Metadata-Version: 2.1
Name: pycartnext
Version: 0.1.1
Summary: 
License: MIT
Author: MahmudulHassan5809
Author-email: mahmudul.hassan240@gmail.com
Requires-Python: >=3.12,<4.0
Classifier: License :: OSI Approved :: MIT License
Classifier: Programming Language :: Python :: 3
Classifier: Programming Language :: Python :: 3.12
Classifier: Programming Language :: Python :: 3.13
Requires-Dist: pydantic (>=2.10.1,<3.0.0)
Requires-Dist: redis (>=5.2.0,<6.0.0)
